<?xml version="1.0" encoding="UTF-8" ?>
<XMLDB PATH="local/smartdashboard/db" VERSION="20260215" COMMENT="XMLDB file for Moodle local_smartdashboard"
    xmlns:xsi="http://www.w3.org/2001/XMLSchema-instance"
    xsi:noNamespaceSchemaLocation="../../../lib/xmldb/xmldb.xsd"
>
  <TABLES>
    <TABLE NAME="local_smartdashboard_reports" COMMENT="Saved custom AI-generated reports">
      <FIELDS>
        <FIELD NAME="id" TYPE="int" LENGTH="10" NOTNULL="true" SEQUENCE="true"/>
        <FIELD NAME="userid" TYPE="int" LENGTH="10" NOTNULL="true" SEQUENCE="false" COMMENT="User who created this report"/>
        <FIELD NAME="title" TYPE="char" LENGTH="255" NOTNULL="true" SEQUENCE="false" COMMENT="Name of the saved report"/>
        <FIELD NAME="description" TYPE="text" NOTNULL="false" SEQUENCE="false" COMMENT="Optional description or original prompt"/>
        <FIELD NAME="sql_query" TYPE="text" NOTNULL="true" SEQUENCE="false" COMMENT="The SQL query to execute"/>
        <FIELD NAME="chart_type" TYPE="char" LENGTH="20" NOTNULL="false" DEFAULT="table" SEQUENCE="false" COMMENT="Preferred visualization type"/>
        <FIELD NAME="timecreated" TYPE="int" LENGTH="10" NOTNULL="true" SEQUENCE="false"/>
        <FIELD NAME="timemodified" TYPE="int" LENGTH="10" NOTNULL="true" SEQUENCE="false"/>
      </FIELDS>
      <KEYS>
        <KEY NAME="primary" TYPE="primary" FIELDS="id"/>
        <KEY NAME="fk_userid" TYPE="foreign" FIELDS="userid" REFTABLE="user" REFFIELDS="id"/>
      </KEYS>
      <INDEXES>
        <INDEX NAME="idx_userid" UNIQUE="false" FIELDS="userid"/>
      </INDEXES>
    </TABLE>
  </TABLES>
</XMLDB>
